TRAMbio/__init__.py
TRAMbio/pebble_game/__init__.py
TRAMbio/pebble_game/base_pebble_game.py
TRAMbio/pebble_game/pebble_game.py
TRAMbio/pebble_game/pebble_game_mp.py
TRAMbio/pebble_game/protein_pebble_game.py
TRAMbio/pebble_game/utility_pebble_game_mp.py
TRAMbio/services/__init__.py
TRAMbio/services/core.py
TRAMbio/services/interactions/__init__.py
TRAMbio/services/interactions/_aromatic_interaction_service.py
TRAMbio/services/interactions/_cation_pi_interaction_service.py
TRAMbio/services/interactions/_conect_entry_service.py
TRAMbio/services/interactions/_disulphide_bridge_service.py
TRAMbio/services/interactions/_hydrogen_bond_service.py
TRAMbio/services/interactions/_hydrophobic_potential_interaction_service.py
TRAMbio/services/interactions/_hydrophobic_surface_interaction_service.py
TRAMbio/services/interactions/_link_entry_service.py
TRAMbio/services/interactions/_ss_bond_entry_service.py
TRAMbio/services/interactions/registry.py
TRAMbio/services/interactions/util/__init__.py
TRAMbio/services/interactions/util/_util_hydrogen_bond_service.py
TRAMbio/services/interactions/util/_util_hydrophobic_interaction_service.py
TRAMbio/services/interactions/util/_vdw_smirks_evaluator.py
TRAMbio/services/io/__init__.py
TRAMbio/services/io/_bond_io_service.py
TRAMbio/services/io/_pdb_io_service.py
TRAMbio/services/io/_pymol_io_service.py
TRAMbio/services/io/_xml_io_service.py
TRAMbio/services/io/_xtc_mdanalysis_io_service.py
TRAMbio/services/io/_xtc_mdtraj_io_service.py
TRAMbio/services/io/registry.py
TRAMbio/services/parameter/__init__.py
TRAMbio/services/parameter/_base_parameter.py
TRAMbio/services/parameter/_interaction_parameter.py
TRAMbio/services/parameter/_structure_parameter.py
TRAMbio/services/parameter/_workflow_parameter.py
TRAMbio/services/parameter/registry.py
TRAMbio/services/structure/__init__.py
TRAMbio/services/structure/_pdb_structure_service.py
TRAMbio/services/structure/_xml_structure_service.py
TRAMbio/services/structure/registry.py
trambio-1.0.3.dist-info/METADATA
trambio-1.0.3.dist-info/WHEEL
trambio-1.0.3.dist-info/entry_points.txt
trambio-1.0.3.dist-info/licenses/LICENSE
trambio-1.0.3.dist-info/RECORD
