Metadata-Version: 2.1
Name: TRAMbio
Version: 1.0.3
Summary: Python package for Topological Rigidity Analysis in Molecular Biology (TRAMbio).
Author-Email: Nicolas Handke <nicolas@bioinf.uni-leipzig.de>
Classifier: Programming Language :: Python :: 3
Classifier: Programming Language :: Python :: 3 :: Only
Classifier: Programming Language :: Python :: 3.8
Classifier: Programming Language :: Python :: 3.9
Classifier: Programming Language :: Python :: 3.10
Classifier: License :: OSI Approved :: MIT License
Classifier: Operating System :: OS Independent
Classifier: Intended Audience :: Science/Research
Classifier: Topic :: Scientific/Engineering
Project-URL: Homepage, https://github.com/gate-tec/TRAMbio
Project-URL: Bug Tracker, https://github.com/gate-tec/TRAMbio/issues
Requires-Python: >=3.8
Requires-Dist: loguru
Requires-Dist: tqdm
Requires-Dist: pathvalidate
Requires-Dist: networkx
Requires-Dist: typing-extensions
Requires-Dist: numpy<1.25,>=1.16.2; python_version < "3.9"
Requires-Dist: numpy; python_version >= "3.9"
Provides-Extra: molecule
Requires-Dist: biopandas; extra == "molecule"
Provides-Extra: trajectory
Requires-Dist: biopandas; extra == "trajectory"
Requires-Dist: gsd==1.9.3; platform_system != "Darwin" and python_version < "3.9" and extra == "trajectory"
Requires-Dist: MDAnalysis; (platform_system != "Darwin" or python_version >= "3.9") and extra == "trajectory"
Requires-Dist: mdtraj; extra == "trajectory"
Provides-Extra: xml
Requires-Dist: lxml; extra == "xml"
Provides-Extra: all
Requires-Dist: biopandas; extra == "all"
Requires-Dist: gsd==1.9.3; platform_system != "Darwin" and python_version < "3.9" and extra == "all"
Requires-Dist: MDAnalysis; (platform_system != "Darwin" or python_version >= "3.9") and extra == "all"
Requires-Dist: mdtraj; extra == "all"
Requires-Dist: lxml; extra == "all"
